brexit/__init__.py
brexit/brexit.py
brexit/cli.py
brexit-0.1.0.dist-info/DESCRIPTION.rst
brexit-0.1.0.dist-info/METADATA
brexit-0.1.0.dist-info/RECORD
brexit-0.1.0.dist-info/WHEEL
brexit-0.1.0.dist-info/entry_points.txt
brexit-0.1.0.dist-info/metadata.json
brexit-0.1.0.dist-info/top_level.txt
