Metadata-Version: 2.0
Name: brexit
Version: 0.1.0
Summary: People's vote...
Home-page: https://github.com/ssbarnea/brexit
Author: Sorin Sbarnea
Author-email: sorin.sbarnea@gmail.com
License: Apache Software License 2.0
Keywords: brexit
Platform: UNKNOWN
Classifier: Development Status :: 2 - Pre-Alpha
Classifier: Intended Audience :: Developers
Classifier: License :: OSI Approved :: Apache Software License
Classifier: Natural Language :: English
Classifier: Programming Language :: Python :: 2
Classifier: Programming Language :: Python :: 2.7
Classifier: Programming Language :: Python :: 3
Classifier: Programming Language :: Python :: 3.4
Classifier: Programming Language :: Python :: 3.5
Classifier: Programming Language :: Python :: 3.6
Classifier: Programming Language :: Python :: 3.7
Requires-Dist: Click (>=6.0)
